hooks_mcp/__init__.py
hooks_mcp/config.py
hooks_mcp/executor.py
hooks_mcp/server.py
hooks_mcp/utils.py
hooks_mcp-0.2.3.dist-info/METADATA
hooks_mcp-0.2.3.dist-info/WHEEL
hooks_mcp-0.2.3.dist-info/entry_points.txt
hooks_mcp-0.2.3.dist-info/licenses/LICENSE.txt
hooks_mcp-0.2.3.dist-info/RECORD
