Metadata-Version: 2.4
Name: hooks-mcp
Version: 0.2.3
Summary: MCP server that exposes project-specific development tools (tests, linters, etc.) and prompts via YAML configuration
Project-URL: Homepage, https://github.com/scosman/hooks_mcp
Project-URL: Repository, https://github.com/scosman/hooks_mcp
Author: Steve Cosman
License-Expression: MIT
License-File: LICENSE.txt
Requires-Python: >=3.10
Requires-Dist: mcp>=1.0.0
Requires-Dist: python-dotenv>=1.0.0
Requires-Dist: pyyaml>=6.0
Requires-Dist: starlette
Requires-Dist: uvicorn
